MANIFEST.in
README.rst
setup.py
Pytwcla/__init__.py
Pytwcla/__main__.py
Pytwcla/key.py
Pytwcla/pytwcla.py
Pytwcla.egg-info/PKG-INFO
Pytwcla.egg-info/SOURCES.txt
Pytwcla.egg-info/dependency_links.txt
Pytwcla.egg-info/entry_points.txt
Pytwcla.egg-info/not-zip-safe
Pytwcla.egg-info/requires.txt
Pytwcla.egg-info/top_level.txt
Pytwcla/keydata/empty.txt
Pytwcla/userconfig/api.ini