Metadata-Version: 1.1
Name: Pytwcla
Version: 0.1.5
Summary: Command-line app for collecting keyword-based Twitter data.
Home-page: http://github.com/akisxyz/pytwcla
Author: akisxyz
Author-email: UNKNOWN
License: MIT
Keywords: twitter,search,stream,database
Platform: UNKNOWN
Classifier: License :: OSI Approved :: MIT License
Classifier: Programming Language :: Python :: 2
Classifier: Programming Language :: Python :: 2.7
Classifier: Programming Language :: Python :: 3
Classifier: Programming Language :: Python :: 3.4
